xplug/__init__.py
xplug-0.0.2.dist-info/LICENSES.txt
xplug-0.0.2.dist-info/METADATA
xplug-0.0.2.dist-info/WHEEL
xplug-0.0.2.dist-info/top_level.txt
xplug-0.0.2.dist-info/RECORD
